OneBitAdder.v
module OneBitAdder (
  // Inputs.
  input x,
  input y,
  input carry_in,

  // Outputs.
  output sum,
  output carry_out
);
    // Description of the logic goes here.
    wire x_not;
    wire y_not;
    wire carry_in_not;
    wire i1, i2, i3, i4, i5, i6, i7, i8, i9, i10;

    assign x_not = ~x;
    assign y_not = ~y;
    assign carry_in_not = ~carry_in;

    // Let's describe circuit for sum.
    assign i1 = x_not & y_not;
    assign i5 = carry_in & i1;

    assign i2 = x_not & y;
    assign i6 = carry_in_not & i2;

    assign i3 = x_not & y;
    assign i7 = carry_in_not & i3;

    assign i4 = x & y;
    assign i8 = carry_in & i4;

    assign i9 = i5 | i6;
    assign i10 = i7 | i8;

    assign sum = i9 | i10;

    // Carry out description.
    assign carry_out = (x & carry_in) | (y & carry_in) | (x & y);

endmodule

one_bit_adder.vcd
$version Generated by VerilatedVcd $end
$date Sun Feb 20 21:36:34 2022
 $end
$timescale   1ps $end

 $scope module TOP $end
  $var wire  1 % carry_in $end
  $var wire  1 ' carry_out $end
  $var wire  1 & sum $end
  $var wire  1 # x $end
  $var wire  1 $ y $end
  $scope module OneBitAdder $end
   $var wire  1 % carry_in $end
   $var wire  1 * carry_in_not $end
   $var wire  1 ' carry_out $end
   $var wire  1 + i1 $end
   $var wire  1 2 i10 $end
   $var wire  1 , i2 $end
   $var wire  1 , i3 $end
   $var wire  1 - i4 $end
   $var wire  1 . i5 $end
   $var wire  1 / i6 $end
   $var wire  1 / i7 $end
   $var wire  1 0 i8 $end
   $var wire  1 1 i9 $end
   $var wire  1 & sum $end
   $var wire  1 # x $end
   $var wire  1 ( x_not $end
   $var wire  1 $ y $end
   $var wire  1 ) y_not $end
  $upscope $end
 $upscope $end
$enddefinitions $end


#1
1#
0$
0%
0&
0'
0(
1)
1*
0+
0,
0-
0.
0/
00
01
02
#2
1$
1'
0)
1-
#3
#4
0#
0$
0'
1(
1)
1+
0-
#5
1#
1$
1'
0(
0)
0+
1-
#6
0#
1&
0'
1(
1,
0-
1/
11
12
#7
#8
1#
0$
0&
0(
1)
0,
0/
01
02
#9
0#
1(
1+
#10
#11
1#
0(
0+
#12
1$
1'
0)
1-
#13
0#
0$
0'
1(
1)
1+
0-
#14
1$
1&
0)
0+
1,
1/
11
12
#15
1#
0&
1'
0(
0,
1-
0/
01
02
#16
0$
0'
1)
0-
#17
0#
1(
1+
#18
1#
1$
1'
0(
0)
0+
1-
#19
0$
0'
1)
0-
#20
#21
1$
1'
0)
1-
#22
#23
0#
1&
0'
1(
1,
0-
1/
11
12
#24
0$
0&
1)
1+
0,
0/
01
02
#25
1#
0(
0+
#26
#27
#28
0#
1$
1&
1(
0)
1,
1/
11
12
#29
0$
0&
1)
1+
0,
0/
01
02
#30
1$
1&
0)
0+
1,
1/
11
12
#31
1#
0&
1'
0(
0,
1-
0/
01
02
#32
0#
1&
0'
1(
1,
0-
1/
11
12
#33
#34
#35
1#
0&
1'
0(
0,
1-
0/
01
02
#36
0#
1&
0'
1(
1,
0-
1/
11
12
#37
#38
#39
0$
0&
1)
1+
0,
0/
01
02
#40
1#
0(
0+
#41
#42
0#
1(
1+
#43
#44
1#
1$
1'
0(
0)
0+
1-
#45
0#
1&
0'
1(
1,
0-
1/
11
12
#46
0$
0&
1)
1+
0,
0/
01
02
#47
#48
1#
0(
0+
#49
0#
1(
1+
#50
1$
1&
0)
0+
1,
1/
11
12
#51
1#
0$
0&
0(
1)
0,
0/
01
02
#52
0#
1(
1+
#53
1#
1$
1'
0(
0)
0+
1-
#54
0$
0'
1)
0-
#55
#56
0#
1(
1+
#57
1#
0(
0+
#58
0#
1$
1&
1(
0)
1,
1/
11
12
#59
1#
0&
1'
0(
0,
1-
0/
01
02
#60
0#
1&
0'
1(
1,
0-
1/
11
12
#61
#62
1#
0&
1'
0(
0,
1-
0/
01
02
#63
#64
#65
#66
0$
0'
1)
0-
#67
1$
1'
0)
1-
#68
0#
1&
0'
1(
1,
0-
1/
11
12
#69
#70
1#
0$
0&
0(
1)
0,
0/
01
02
#71
0#
1$
1&
1(
0)
1,
1/
11
12
#72
#73
1#
0&
1'
0(
0,
1-
0/
01
02
#74
0#
0$
0'
1(
1)
1+
0-
#75
1$
1&
0)
0+
1,
1/
11
12
#76
#77
#78
#79
#80
1#
0&
1'
0(
0,
1-
0/
01
02
#81
0$
0'
1)
0-
#82
0#
1(
1+
#83
1#
0(
0+
#84
#85
0#
1(
1+
#86
#87
1#
0(
0+
#88
1$
1'
0)
1-
#89
#90
0$
0'
1)
0-
#91
0#
1$
1&
1(
0)
1,
1/
11
12
#92
1#
0$
0&
0(
1)
0,
0/
01
02
#93
1$
1'
0)
1-
#94
0#
1&
0'
1(
1,
0-
1/
11
12
#95
#96
1#
0&
1'
0(
0,
1-
0/
01
02
#97
#98
0#
0$
0'
1(
1)
1+
0-
#99
1#
1$
1'
0(
0)
0+
1-
#100
0#
1&
0'
1(
1,
0-
1/
11
12
#101
0$
0&
1)
1+
0,
0/
01
02
#102
1#
1$
1'
0(
0)
0+
1-
#103
0$
0'
1)
0-
#104
0#
1(
1+
#105
#106
#107
1#
1$
1'
0(
0)
0+
1-
#108
0$
0'
1)
0-
#109
0#
1$
1&
1(
0)
1,
1/
11
12
#110
#111
#112
#113
0$
0&
1)
1+
0,
0/
01
02
#114
1#
1$
1'
0(
0)
0+
1-
#115
0#
0$
0'
1(
1)
1+
0-
#116
1#
0(
0+
#117
0#
1(
1+
#118
1#
1$
1'
0(
0)
0+
1-
#119
0$
0'
1)
0-
#120
0#
1$
1&
1(
0)
1,
1/
11
12
#121
0$
0&
1)
1+
0,
0/
01
02
#122
1#
1$
1'
0(
0)
0+
1-
#123
0#
0$
0'
1(
1)
1+
0-
#124
#125
1#
0(
0+
#126
1$
1'
0)
1-
#127
0$
0'
1)
0-
#128
0#
1$
1&
1(
0)
1,
1/
11
12
#129
0$
0&
1)
1+
0,
0/
01
02
#130
#131
1$
1&
0)
0+
1,
1/
11
12
#132
0$
0&
1)
1+
0,
0/
01
02
#133
#134
1$
1&
0)
0+
1,
1/
11
12
#135
0$
0&
1)
1+
0,
0/
01
02
#136
#137
1$
1&
0)
0+
1,
1/
11
12
#138
1#
0$
0&
0(
1)
0,
0/
01
02
#139
0#
1$
1&
1(
0)
1,
1/
11
12
#140
1#
0&
1'
0(
0,
1-
0/
01
02
#141
0$
0'
1)
0-
#142
#143
0#
1$
1&
1(
0)
1,
1/
11
12
#144
1#
0&
1'
0(
0,
1-
0/
01
02
#145
0$
0'
1)
0-
#146
1$
1'
0)
1-
#147
0$
0'
1)
0-
#148
0#
1$
1&
1(
0)
1,
1/
11
12
#149
0$
0&
1)
1+
0,
0/
01
02
#150
#151
#152
#153
1$
1&
0)
0+
1,
1/
11
12
#154
1#
0$
0&
0(
1)
0,
0/
01
02
#155
#156
#157
0#
1(
1+
#158
1#
1$
1'
0(
0)
0+
1-
#159
0#
0$
0'
1(
1)
1+
0-
#160
1$
1&
0)
0+
1,
1/
11
12
#161
#162
1#
0$
0&
0(
1)
0,
0/
01
02
#163
1$
1'
0)
1-
#164
#165
0$
0'
1)
0-
#166
1$
1'
0)
1-
#167
0#
1&
0'
1(
1,
0-
1/
11
12
#168
1#
0$
0&
0(
1)
0,
0/
01
02
#169
#170
0#
1(
1+
#171
#172
1$
1&
0)
0+
1,
1/
11
12
#173
#174
0$
0&
1)
1+
0,
0/
01
02
#175
#176
#177
1#
1$
1'
0(
0)
0+
1-
#178
0#
1&
0'
1(
1,
0-
1/
11
12
#179
0$
0&
1)
1+
0,
0/
01
02
#180
1$
1&
0)
0+
1,
1/
11
12
#181
0$
0&
1)
1+
0,
0/
01
02
#182
#183
1#
1$
1'
0(
0)
0+
1-
#184
0$
0'
1)
0-
#185
0#
1$
1&
1(
0)
1,
1/
11
12
#186
0$
0&
1)
1+
0,
0/
01
02
#187
1#
1$
1'
0(
0)
0+
1-
#188
0$
0'
1)
0-
#189
0#
1$
1&
1(
0)
1,
1/
11
12
#190
0$
0&
1)
1+
0,
0/
01
02
#191
1#
0(
0+
#192
1$
1'
0)
1-
#193
#194
0#
1&
0'
1(
1,
0-
1/
11
12
#195
1#
0$
0&
0(
1)
0,
0/
01
02
#196
0#
1$
1&
1(
0)
1,
1/
11
12
#197
0$
0&
1)
1+
0,
0/
01
02
#198
#199
1$
1&
0)
0+
1,
1/
11
12
#200
0$
0&
1)
1+
0,
0/
01
02
#201
1$
1&
0)
0+
1,
1/
11
12
#202
0$
0&
1)
1+
0,
0/
01
02
#203
#204
#205
1#
0(
0+
#206
1$
1'
0)
1-
#207
0$
0'
1)
0-
#208
0#
1(
1+
#209
1#
0(
0+
#210
0#
1$
1&
1(
0)
1,
1/
11
12
#211
0$
0&
1)
1+
0,
0/
01
02
#212
1$
1&
0)
0+
1,
1/
11
12
#213
1#
0$
0&
0(
1)
0,
0/
01
02
#214
1$
1'
0)
1-
#215
#216
0$
0'
1)
0-
#217
0#
1$
1&
1(
0)
1,
1/
11
12
#218
0$
0&
1)
1+
0,
0/
01
02
#219
1#
0(
0+
#220
1$
1'
0)
1-
#221
0#
0$
0'
1(
1)
1+
0-
#222
1$
1&
0)
0+
1,
1/
11
12
#223
0$
0&
1)
1+
0,
0/
01
02
#224
1$
1&
0)
0+
1,
1/
11
12
#225
0$
0&
1)
1+
0,
0/
01
02
#226
#227
1$
1&
0)
0+
1,
1/
11
12
#228
1#
0&
1'
0(
0,
1-
0/
01
02
#229
0$
0'
1)
0-
#230
0#
1$
1&
1(
0)
1,
1/
11
12
#231
#232
1#
0$
0&
0(
1)
0,
0/
01
02
#233
1$
1'
0)
1-
#234
0$
0'
1)
0-
#235
#236
1$
1'
0)
1-
#237
0#
1&
0'
1(
1,
0-
1/
11
12
#238
1#
0$
0&
0(
1)
0,
0/
01
02
#239
1$
1'
0)
1-
#240
#241
0$
0'
1)
0-
#242
0#
1$
1&
1(
0)
1,
1/
11
12
#243
1#
0&
1'
0(
0,
1-
0/
01
02
#244
0$
0'
1)
0-
#245
0#
1$
1&
1(
0)
1,
1/
11
12
#246
1#
0$
0&
0(
1)
0,
0/
01
02
#247
#248
0#
1(
1+
#249
1#
1$
1'
0(
0)
0+
1-
#250
0#
0$
0'
1(
1)
1+
0-
#251
1#
0(
0+
#252
0#
1$
1&
1(
0)
1,
1/
11
12
#253
1#
0&
1'
0(
0,
1-
0/
01
02
#254
#255
0#
1&
0'
1(
1,
0-
1/
11
12
#256
#257
1#
0$
0&
0(
1)
0,
0/
01
02
#258
0#
1(
1+
#259
1$
1&
0)
0+
1,
1/
11
12
#260
0$
0&
1)
1+
0,
0/
01
02
#261
1#
0(
0+
#262
0#
1(
1+
#263
#264
#265
#266
1$
1&
0)
0+
1,
1/
11
12
#267
0$
0&
1)
1+
0,
0/
01
02
#268
1#
0(
0+
#269
#270
1$
1'
0)
1-
#271
#272
0#
0$
0'
1(
1)
1+
0-
#273
1$
1&
0)
0+
1,
1/
11
12
#274
0$
0&
1)
1+
0,
0/
01
02
#275
1$
1&
0)
0+
1,
1/
11
12
#276
#277
1#
0$
0&
0(
1)
0,
0/
01
02
#278
1$
1'
0)
1-
#279
0#
1&
0'
1(
1,
0-
1/
11
12
#280
1#
0$
0&
0(
1)
0,
0/
01
02
#281
0#
1(
1+
#282
#283
1$
1&
0)
0+
1,
1/
11
12
#284
0$
0&
1)
1+
0,
0/
01
02
#285
1#
1$
1'
0(
0)
0+
1-
#286
#287
0$
0'
1)
0-
#288
1$
1'
0)
1-
#289
0$
0'
1)
0-
#290
1$
1'
0)
1-
#291
#292
0$
0'
1)
0-
#293
#294
1$
1'
0)
1-
#295
0#
1&
0'
1(
1,
0-
1/
11
12
#296
0$
0&
1)
1+
0,
0/
01
02
#297
1#
0(
0+
#298
0#
1$
1&
1(
0)
1,
1/
11
12
#299
1#
0&
1'
0(
0,
1-
0/
01
02
#300
0$
0'
1)
0-
#301
0#
1$
1&
1(
0)
1,
1/
11
12
#302
1#
0&
1'
0(
0,
1-
0/
01
02
#303
#304
0#
0$
0'
1(
1)
1+
0-
#305
1#
1$
1'
0(
0)
0+
1-
#306
0$
0'
1)
0-
#307
0#
1(
1+
#308
1$
1&
0)
0+
1,
1/
11
12
#309
1#
0&
1'
0(
0,
1-
0/
01
02
#310
#311
0#
1&
0'
1(
1,
0-
1/
11
12
#312
1#
0&
1'
0(
0,
1-
0/
01
02
#313
#314
0$
0'
1)
0-
#315
0#
1(
1+
#316
1$
1&
0)
0+
1,
1/
11
12
#317
1#
0$
0&
0(
1)
0,
0/
01
02
#318
0#
1(
1+
#319
1#
1$
1'
0(
0)
0+
1-
#320
0#
0$
0'
1(
1)
1+
0-
#321
#322
1$
1&
0)
0+
1,
1/
11
12
#323
0$
0&
1)
1+
0,
0/
01
02
#324
1$
1&
0)
0+
1,
1/
11
12
#325
1#
0&
1'
0(
0,
1-
0/
01
02
#326
0#
0$
0'
1(
1)
1+
0-
#327
1$
1&
0)
0+
1,
1/
11
12
#328
1#
0&
1'
0(
0,
1-
0/
01
02
#329
0$
0'
1)
0-
#330
1$
1'
0)
1-
#331
0$
0'
1)
0-
#332
0#
1(
1+
#333
1$
1&
0)
0+
1,
1/
11
12
#334
1#
0&
1'
0(
0,
1-
0/
01
02
#335
0#
1&
0'
1(
1,
0-
1/
11
12
#336
1#
0$
0&
0(
1)
0,
0/
01
02
#337
1$
1'
0)
1-
#338
0$
0'
1)
0-
#339
#340
#341
#342
0#
1(
1+
#343
1#
0(
0+
#344
#345
0#
1$
1&
1(
0)
1,
1/
11
12
#346
#347
1#
0$
0&
0(
1)
0,
0/
01
02
#348
0#
1$
1&
1(
0)
1,
1/
11
12
#349
1#
0&
1'
0(
0,
1-
0/
01
02
#350
0#
1&
0'
1(
1,
0-
1/
11
12
#351
#352
0$
0&
1)
1+
0,
0/
01
02
#353
1$
1&
0)
0+
1,
1/
11
12
#354
#355
1#
0&
1'
0(
0,
1-
0/
01
02
#356
#357
0$
0'
1)
0-
#358
1$
1'
0)
1-
#359
0#
0$
0'
1(
1)
1+
0-
#360
1#
0(
0+
#361
1$
1'
0)
1-
#362
0#
0$
0'
1(
1)
1+
0-
#363
#364
1#
1$
1'
0(
0)
0+
1-
#365
#366
#367
0#
1&
0'
1(
1,
0-
1/
11
12
#368
1#
0$
0&
0(
1)
0,
0/
01
02
#369
0#
1$
1&
1(
0)
1,
1/
11
12
#370
1#
0$
0&
0(
1)
0,
0/
01
02
#371
1$
1'
0)
1-
#372
0$
0'
1)
0-
#373
#374
1$
1'
0)
1-
#375
0#
1&
0'
1(
1,
0-
1/
11
12
#376
1#
0$
0&
0(
1)
0,
0/
01
02
#377
0#
1$
1&
1(
0)
1,
1/
11
12
#378
0$
0&
1)
1+
0,
0/
01
02
#379
1#
0(
0+
#380
0#
1(
1+
#381
1#
1$
1'
0(
0)
0+
1-
#382
0#
0$
0'
1(
1)
1+
0-
#383
1$
1&
0)
0+
1,
1/
11
12
#384
0$
0&
1)
1+
0,
0/
01
02
#385
1#
0(
0+
#386
0#
1(
1+
#387
1#
1$
1'
0(
0)
0+
1-
#388
0#
0$
0'
1(
1)
1+
0-
#389
1#
0(
0+
#390
#391
#392
0#
1$
1&
1(
0)
1,
1/
11
12
#393
0$
0&
1)
1+
0,
0/
01
02
#394
1$
1&
0)
0+
1,
1/
11
12
#395
0$
0&
1)
1+
0,
0/
01
02
#396
#397
1#
0(
0+
#398
0#
1$
1&
1(
0)
1,
1/
11
12
#399
1#
0$
0&
0(
1)
0,
0/
01
02
#400
#401
0#
1(
1+
#402
1$
1&
0)
0+
1,
1/
11
12
#403
1#
0&
1'
0(
0,
1-
0/
01
02
#404
#405
0$
0'
1)
0-
#406
#407
1$
1'
0)
1-
#408
#409
#410
0#
0$
0'
1(
1)
1+
0-
#411
1#
0(
0+
#412
0#
1(
1+
#413
#414
1#
0(
0+
#415
0#
1$
1&
1(
0)
1,
1/
11
12
#416
#417
1#
0&
1'
0(
0,
1-
0/
01
02
#418
0#
0$
0'
1(
1)
1+
0-
#419
#420
1#
1$
1'
0(
0)
0+
1-
#421
0#
0$
0'
1(
1)
1+
0-
#422
1#
1$
1'
0(
0)
0+
1-
#423
0$
0'
1)
0-
#424
0#
1$
1&
1(
0)
1,
1/
11
12
#425
#426
1#
0&
1'
0(
0,
1-
0/
01
02
#427
#428
0#
0$
0'
1(
1)
1+
0-
#429
1#
1$
1'
0(
0)
0+
1-
#430
0#
1&
0'
1(
1,
0-
1/
11
12
#431
0$
0&
1)
1+
0,
0/
01
02
#432
1$
1&
0)
0+
1,
1/
11
12
#433
1#
0&
1'
0(
0,
1-
0/
01
02
#434
0#
1&
0'
1(
1,
0-
1/
11
12
#435
1#
0&
1'
0(
0,
1-
0/
01
02
#436
0#
1&
0'
1(
1,
0-
1/
11
12
#437
#438
1#
0&
1'
0(
0,
1-
0/
01
02
#439
0#
1&
0'
1(
1,
0-
1/
11
12
#440
0$
0&
1)
1+
0,
0/
01
02
#441
1$
1&
0)
0+
1,
1/
11
12
#442
1#
0$
0&
0(
1)
0,
0/
01
02
#443
0#
1$
1&
1(
0)
1,
1/
11
12
#444
#445
1#
0$
0&
0(
1)
0,
0/
01
02
#446
1$
1'
0)
1-
#447
0#
1&
0'
1(
1,
0-
1/
11
12
#448
1#
0$
0&
0(
1)
0,
0/
01
02
#449
0#
1$
1&
1(
0)
1,
1/
11
12
#450
1#
0&
1'
0(
0,
1-
0/
01
02
#451
0#
0$
0'
1(
1)
1+
0-
#452
1#
0(
0+
#453
#454
0#
1$
1&
1(
0)
1,
1/
11
12
#455
1#
0$
0&
0(
1)
0,
0/
01
02
#456
#457
0#
1$
1&
1(
0)
1,
1/
11
12
#458
0$
0&
1)
1+
0,
0/
01
02
#459
#460
1$
1&
0)
0+
1,
1/
11
12
#461
#462
1#
0$
0&
0(
1)
0,
0/
01
02
#463
0#
1(
1+
#464
1$
1&
0)
0+
1,
1/
11
12
#465
1#
0$
0&
0(
1)
0,
0/
01
02
#466
0#
1$
1&
1(
0)
1,
1/
11
12
#467
#468
#469
1#
0$
0&
0(
1)
0,
0/
01
02
#470
1$
1'
0)
1-
#471
0#
0$
0'
1(
1)
1+
0-
#472
1#
0(
0+
#473
1$
1'
0)
1-
#474
0$
0'
1)
0-
#475
1$
1'
0)
1-
#476
#477
0#
0$
0'
1(
1)
1+
0-
#478
1#
0(
0+
#479
0#
1(
1+
#480
1#
1$
1'
0(
0)
0+
1-
#481
0#
0$
0'
1(
1)
1+
0-
#482
1#
0(
0+
#483
1$
1'
0)
1-
#484
#485
0$
0'
1)
0-
#486
0#
1$
1&
1(
0)
1,
1/
11
12
#487
1#
0&
1'
0(
0,
1-
0/
01
02
#488
0#
0$
0'
1(
1)
1+
0-
#489
1$
1&
0)
0+
1,
1/
11
12
#490
#491
0$
0&
1)
1+
0,
0/
01
02
#492
#493
1$
1&
0)
0+
1,
1/
11
12
#494
#495
1#
0$
0&
0(
1)
0,
0/
01
02
#496
0#
1$
1&
1(
0)
1,
1/
11
12
#497
#498
1#
0&
1'
0(
0,
1-
0/
01
02
#499
0#
1&
0'
1(
1,
0-
1/
11
12
#500
#501
1#
0$
0&
0(
1)
0,
0/
01
02
#502
#503
1$
1'
0)
1-
#504
#505
0#
1&
0'
1(
1,
0-
1/
11
12
#506
0$
0&
1)
1+
0,
0/
01
02
#507
1#
0(
0+
#508
0#
1(
1+
#509
#510
1#
1$
1'
0(
0)
0+
1-
#511
0#
1&
0'
1(
1,
0-
1/
11
12
#512
1#
0$
0&
0(
1)
0,
0/
01
02
#513
#514
0#
1$
1&
1(
0)
1,
1/
11
12
#515
1#
0$
0&
0(
1)
0,
0/
01
02
#516
1$
1'
0)
1-
#517
0$
0'
1)
0-
#518
#519
#520
0#
1$
1&
1(
0)
1,
1/
11
12
#521
0$
0&
1)
1+
0,
0/
01
02
#522
1#
1$
1'
0(
0)
0+
1-
#523
#524
#525
0$
0'
1)
0-
#526
0#
1(
1+
#527
1$
1&
0)
0+
1,
1/
11
12
#528
#529
0$
0&
1)
1+
0,
0/
01
02
#530
1$
1&
0)
0+
1,
1/
11
12
#531
1#
0&
1'
0(
0,
1-
0/
01
02
#532
0#
0$
0'
1(
1)
1+
0-
#533
1#
0(
0+
#534
0#
1(
1+
#535
#536
1#
0(
0+
#537
#538
0#
1(
1+
#539
1#
1$
1'
0(
0)
0+
1-
#540
#541
0#
1&
0'
1(
1,
0-
1/
11
12
#542
1#
0$
0&
0(
1)
0,
0/
01
02
#543
1$
1'
0)
1-
#544
#545
0#
1&
0'
1(
1,
0-
1/
11
12
#546
#547
1#
0&
1'
0(
0,
1-
0/
01
02
#548
0$
0'
1)
0-
#549
1$
1'
0)
1-
#550
#551
0#
0$
0'
1(
1)
1+
0-
#552
1$
1&
0)
0+
1,
1/
11
12
#553
1#
0$
0&
0(
1)
0,
0/
01
02
#554
#555
#556
1$
1'
0)
1-
#557
0$
0'
1)
0-
#558
#559
0#
1(
1+
#560
1#
0(
0+
#561
0#
1(
1+
#562
1#
1$
1'
0(
0)
0+
1-
#563
0$
0'
1)
0-
#564
#565
#566
1$
1'
0)
1-
#567
#568
0#
0$
0'
1(
1)
1+
0-
#569
1#
1$
1'
0(
0)
0+
1-
#570
0#
1&
0'
1(
1,
0-
1/
11
12
#571
1#
0$
0&
0(
1)
0,
0/
01
02
#572
0#
1$
1&
1(
0)
1,
1/
11
12
#573
0$
0&
1)
1+
0,
0/
01
02
#574
1#
0(
0+
#575
0#
1$
1&
1(
0)
1,
1/
11
12
#576
0$
0&
1)
1+
0,
0/
01
02
#577
1#
1$
1'
0(
0)
0+
1-
#578
0$
0'
1)
0-
#579
1$
1'
0)
1-
#580
0#
1&
0'
1(
1,
0-
1/
11
12
#581
1#
0&
1'
0(
0,
1-
0/
01
02
#582
0#
0$
0'
1(
1)
1+
0-
#583
1#
1$
1'
0(
0)
0+
1-
#584
0#
0$
0'
1(
1)
1+
0-
#585
1$
1&
0)
0+
1,
1/
11
12
#586
1#
0$
0&
0(
1)
0,
0/
01
02
#587
#588
1$
1'
0)
1-
#589
0#
0$
0'
1(
1)
1+
0-
#590
#591
1#
0(
0+
#592
#593
0#
1(
1+
#594
1$
1&
0)
0+
1,
1/
11
12
#595
1#
0$
0&
0(
1)
0,
0/
01
02
#596
0#
1$
1&
1(
0)
1,
1/
11
12
#597
#598
1#
0&
1'
0(
0,
1-
0/
01
02
#599
0#
0$
0'
1(
1)
1+
0-
#600
1#
0(
0+
#601
1$
1'
0)
1-
#602
0#
0$
0'
1(
1)
1+
0-
#603
1#
1$
1'
0(
0)
0+
1-
#604
#605
0#
1&
0'
1(
1,
0-
1/
11
12
#606
1#
0&
1'
0(
0,
1-
0/
01
02
#607
0#
0$
0'
1(
1)
1+
0-
#608
#609
1#
0(
0+
#610
#611
#612
1$
1'
0)
1-
#613
#614
0#
1&
0'
1(
1,
0-
1/
11
12
#615
1#
0&
1'
0(
0,
1-
0/
01
02
#616
0$
0'
1)
0-
#617
0#
1(
1+
#618
1$
1&
0)
0+
1,
1/
11
12
#619
1#
0&
1'
0(
0,
1-
0/
01
02
#620
0#
1&
0'
1(
1,
0-
1/
11
12
#621
1#
0$
0&
0(
1)
0,
0/
01
02
#622
1$
1'
0)
1-
#623
0#
1&
0'
1(
1,
0-
1/
11
12
#624
1#
0&
1'
0(
0,
1-
0/
01
02
#625
0$
0'
1)
0-
#626
0#
1(
1+
#627
1$
1&
0)
0+
1,
1/
11
12
#628
1#
0&
1'
0(
0,
1-
0/
01
02
#629
0#
1&
0'
1(
1,
0-
1/
11
12
#630
#631
1#
0$
0&
0(
1)
0,
0/
01
02
#632
1$
1'
0)
1-
#633
0#
1&
0'
1(
1,
0-
1/
11
12
#634
1#
0&
1'
0(
0,
1-
0/
01
02
#635
#636
0$
0'
1)
0-
#637
#638
#639
#640
#641
0#
1$
1&
1(
0)
1,
1/
11
12
#642
1#
0&
1'
0(
0,
1-
0/
01
02
#643
0$
0'
1)
0-
#644
0#
1$
1&
1(
0)
1,
1/
11
12
#645
#646
1#
0&
1'
0(
0,
1-
0/
01
02
#647
0$
0'
1)
0-
#648
0#
1$
1&
1(
0)
1,
1/
11
12
#649
#650
#651
1#
0&
1'
0(
0,
1-
0/
01
02
#652
0$
0'
1)
0-
#653
#654
0#
1(
1+
#655
#656
1#
0(
0+
#657
#658
#659
0#
1(
1+
#660
#661
1#
1$
1'
0(
0)
0+
1-
#662
0$
0'
1)
0-
#663
#664
1$
1'
0)
1-
#665
#666
0#
0$
0'
1(
1)
1+
0-
#667
1#
1$
1'
0(
0)
0+
1-
#668
0$
0'
1)
0-
#669
1$
1'
0)
1-
#670
#671
0$
0'
1)
0-
#672
0#
1$
1&
1(
0)
1,
1/
11
12
#673
#674
1#
0$
0&
0(
1)
0,
0/
01
02
#675
1$
1'
0)
1-
#676
0$
0'
1)
0-
#677
0#
1(
1+
#678
#679
1$
1&
0)
0+
1,
1/
11
12
#680
1#
0$
0&
0(
1)
0,
0/
01
02
#681
#682
0#
1(
1+
#683
1#
1$
1'
0(
0)
0+
1-
#684
0#
1&
0'
1(
1,
0-
1/
11
12
#685
1#
0&
1'
0(
0,
1-
0/
01
02
#686
0#
0$
0'
1(
1)
1+
0-
#687
1#
0(
0+
#688
1$
1'
0)
1-
#689
0#
1&
0'
1(
1,
0-
1/
11
12
#690
#691
#692
#693
1#
0$
0&
0(
1)
0,
0/
01
02
#694
#695
0#
1(
1+
#696
1$
1&
0)
0+
1,
1/
11
12
#697
0$
0&
1)
1+
0,
0/
01
02
#698
1#
0(
0+
#699
0#
1$
1&
1(
0)
1,
1/
11
12
#700
1#
0&
1'
0(
0,
1-
0/
01
02
#701
#702
0$
0'
1)
0-
#703
0#
1$
1&
1(
0)
1,
1/
11
12
#704
0$
0&
1)
1+
0,
0/
01
02
#705
#706
1#
0(
0+
#707
1$
1'
0)
1-
#708
0$
0'
1)
0-
#709
0#
1(
1+
#710
#711
1#
0(
0+
#712
1$
1'
0)
1-
#713
0$
0'
1)
0-
#714
1$
1'
0)
1-
#715
0$
0'
1)
0-
#716
0#
1(
1+
#717
1$
1&
0)
0+
1,
1/
11
12
#718
1#
0$
0&
0(
1)
0,
0/
01
02
#719
0#
1$
1&
1(
0)
1,
1/
11
12
#720
0$
0&
1)
1+
0,
0/
01
02
#721
1#
1$
1'
0(
0)
0+
1-
#722
0$
0'
1)
0-
#723
#724
0#
1$
1&
1(
0)
1,
1/
11
12
#725
1#
0&
1'
0(
0,
1-
0/
01
02
#726
0$
0'
1)
0-
#727
#728
#729
0#
1$
1&
1(
0)
1,
1/
11
12
#730
1#
0&
1'
0(
0,
1-
0/
01
02
#731
#732
0#
1&
0'
1(
1,
0-
1/
11
12
#733
1#
0&
1'
0(
0,
1-
0/
01
02
#734
#735
0#
1&
0'
1(
1,
0-
1/
11
12
#736
#737
1#
0&
1'
0(
0,
1-
0/
01
02
#738
0$
0'
1)
0-
#739
1$
1'
0)
1-
#740
0$
0'
1)
0-
#741
0#
1(
1+
#742
#743
#744
#745
1#
0(
0+
#746
#747
1$
1'
0)
1-
#748
0#
0$
0'
1(
1)
1+
0-
#749
1$
1&
0)
0+
1,
1/
11
12
#750
0$
0&
1)
1+
0,
0/
01
02
#751
1#
0(
0+
#752
#753
#754
0#
1(
1+
#755
1$
1&
0)
0+
1,
1/
11
12
#756
1#
0$
0&
0(
1)
0,
0/
01
02
#757
1$
1'
0)
1-
#758
0#
1&
0'
1(
1,
0-
1/
11
12
#759
1#
0&
1'
0(
0,
1-
0/
01
02
#760
0$
0'
1)
0-
#761
#762
#763
0#
1$
1&
1(
0)
1,
1/
11
12
#764
1#
0$
0&
0(
1)
0,
0/
01
02
#765
0#
1$
1&
1(
0)
1,
1/
11
12
#766
1#
0&
1'
0(
0,
1-
0/
01
02
#767
0$
0'
1)
0-
#768
#769
1$
1'
0)
1-
#770
0#
1&
0'
1(
1,
0-
1/
11
12
#771
#772
1#
0&
1'
0(
0,
1-
0/
01
02
#773
0$
0'
1)
0-
#774
0#
1(
1+
#775
1#
1$
1'
0(
0)
0+
1-
#776
0$
0'
1)
0-
#777
0#
1(
1+
#778
#779
1#
1$
1'
0(
0)
0+
1-
#780
0#
1&
0'
1(
1,
0-
1/
11
12
#781
#782
1#
0&
1'
0(
0,
1-
0/
01
02
#783
0#
0$
0'
1(
1)
1+
0-
#784
1#
1$
1'
0(
0)
0+
1-
#785
0#
0$
0'
1(
1)
1+
0-
#786
#787
1#
1$
1'
0(
0)
0+
1-
#788
0#
0$
0'
1(
1)
1+
0-
#789
1#
0(
0+
#790
#791
0#
1(
1+
#792
#793
1$
1&
0)
0+
1,
1/
11
12
#794
#795
0$
0&
1)
1+
0,
0/
01
02
#796
1$
1&
0)
0+
1,
1/
11
12
#797
#798
0$
0&
1)
1+
0,
0/
01
02
#799
#800
1#
0(
0+
#801
0#
1$
1&
1(
0)
1,
1/
11
12
#802
#803
0$
0&
1)
1+
0,
0/
01
02
#804
#805
1#
1$
1'
0(
0)
0+
1-
#806
0#
1&
0'
1(
1,
0-
1/
11
12
#807
1#
0&
1'
0(
0,
1-
0/
01
02
#808
#809
0#
1&
0'
1(
1,
0-
1/
11
12
#810
0$
0&
1)
1+
0,
0/
01
02
#811
1#
0(
0+
#812
1$
1'
0)
1-
#813
0#
0$
0'
1(
1)
1+
0-
#814
1#
0(
0+
#815
0#
1(
1+
#816
#817
1#
0(
0+
#818
#819
1$
1'
0)
1-
#820
0#
0$
0'
1(
1)
1+
0-
#821
#822
1#
1$
1'
0(
0)
0+
1-
#823
0$
0'
1)
0-
#824
0#
1$
1&
1(
0)
1,
1/
11
12
#825
1#
0$
0&
0(
1)
0,
0/
01
02
